luxai_runner/__init__.py
luxai_runner/bot.py
luxai_runner/cli.py
luxai_runner/episode.py
luxai_runner/ext_to_command.py
luxai_runner/logger.py
luxai_runner/process.py
luxai_runner/utils.py
luxai_runner/tournament/__init__.py
luxai_runner/tournament/config.py
luxai_runner/tournament/matchmaking.py
luxai_runner/tournament/rankingsystem.py
luxai_runner/tournament/tournament.py
luxai_s3/__init__.py
luxai_s3/env.py
luxai_s3/globals.py
luxai_s3/params.py
luxai_s3/profiler.py
luxai_s3/pygame_render.py
luxai_s3/spaces.py
luxai_s3/state.py
luxai_s3/utils.py
luxai_s3/wrappers.py
luxai_s3-0.2.1.dist-info/METADATA
luxai_s3-0.2.1.dist-info/WHEEL
luxai_s3-0.2.1.dist-info/entry_points.txt
luxai_s3-0.2.1.dist-info/top_level.txt
luxai_s3-0.2.1.dist-info/RECORD
