Metadata-Version: 2.2
Name: luxai-s3
Version: 0.2.1
Summary: Lux AI Challenge Season 3 environment code
Author: Lux AI Challenge
Requires-Dist: jax
Requires-Dist: gymnax==0.0.8
Requires-Dist: tyro
Dynamic: author
Dynamic: requires-dist
Dynamic: summary
